{"timestamp": "2025-03-28T00:11:20.683715", "url": "https://jandan.net/api/tucao/list/5877938", "method": "GET", "response": {"success": true, "status_code": 200, "url": "https://jandan.net/api/tucao/list/5877938", "headers": {"Server": "Tengine", "Content-Type": "application/json; charset=UTF-8", "Transfer-Encoding": "chunked", "Connection": "keep-alive", "Date": "Thu, 27 Mar 2025 16:11:20 GMT", "Vary": "Accept-Encoding", "Expires": "Thu, 27 Mar 2025 16:11:19 GMT", "Cache-Control": "no-cache", "X-Powered-By": "PHP/5.2.10", "Content-Encoding": "gzip", "Via": "cache35.l2cn7769[70,70,200-0,M], cache40.l2cn7769[71,0], kunlun18.cn5230[74,73,200-0,M], kunlun7.cn5230[76,0]", "Ali-Swift-Global-Savetime": "1743091880", "X-Cache": "MISS TCP_MISS dirn:-2:-2", "X-Swift-SaveTime": "Thu, 27 Mar 2025 16:11:20 GMT", "X-Swift-CacheTime": "0", "Timing-Allow-Origin": "*", "EagleId": "6f30472417430918807294579e"}, "content_type": "application/json; charset=UTF-8", "text": "{\"code\":0,\"hot_tucao\":[{\"comment_ID\":13020772,\"comment_post_ID\":102312,\"comment_topic\":\"\",\"comment_author\":\"阳光彩虹小白马\",\"comment_date\":\"2025-03-27 13:24:57\",\"comment_date_int\":1743053097,\"comment_content\":\"  \\u003ca href=\\\"#tucao-13020417\\\" data-id=\\\"13020417\\\" class=\\\"tucao-link\\\"\\u003e@蛋友24cd5cbbf97c\\u003c/a\\u003e  这条树洞跟婚姻有什么关系？。。\",\"comment_parent\":5877938,\"comment_reply_ID\":0,\"is_jandan_user\":1,\"is_tip_user\":0,\"vote_positive\":8,\"vote_negative\":0,\"sub_comment_count\":0,\"images\":null,\"ip_location\":\"山东省临沂市\"}],\"tucao\":[{\"comment_ID\":13020417,\"comment_post_ID\":102312,\"comment_topic\":\"\",\"comment_author\":\"蛋友24cd5cbbf97c\",\"comment_date\":\"2025-03-27 11:37:25\",\"comment_date_int\":1743046645,\"comment_content\":\"所以婚姻确实会带来很多问题，单身时候 你只有自己寂寞的问题\",\"comment_parent\":5877938,\"comment_reply_ID\":0,\"is_jandan_user\":1,\"is_tip_user\":0,\"vote_positive\":0,\"vote_negative\":5,\"sub_comment_count\":0,\"images\":null,\"ip_location\":\"广东省佛山市\"},{\"comment_ID\":13020490,\"comment_post_ID\":102312,\"comment_topic\":\"\",\"comment_author\":\"菠萝包\",\"comment_date\":\"2025-03-27 11:58:22\",\"comment_date_int\":1743047902,\"comment_content\":\"  \\u003ca href=\\\"#tucao-13020417\\\" data-id=\\\"13020417\\\" class=\\\"tucao-link\\\"\\u003e@蛋友24cd5cbbf97c\\u003c/a\\u003e 多个单身一起玩是不是不寂寞了啊\",\"comment_parent\":5877938,\"comment_reply_ID\":0,\"is_jandan_user\":1,\"is_tip_user\":0,\"vote_positive\":0,\"vote_negative\":0,\"sub_comment_count\":0,\"images\":null,\"ip_location\":\"上海市宝山区\"},{\"comment_ID\":13020772,\"comment_post_ID\":102312,\"comment_topic\":\"\",\"comment_author\":\"阳光彩虹小白马\",\"comment_date\":\"2025-03-27 13:24:57\",\"comment_date_int\":1743053097,\"comment_content\":\"  \\u003ca href=\\\"#tucao-13020417\\\" data-id=\\\"13020417\\\" class=\\\"tucao-link\\\"\\u003e@蛋友24cd5cbbf97c\\u003c/a\\u003e  这条树洞跟婚姻有什么关系？。。\",\"comment_parent\":5877938,\"comment_reply_ID\":0,\"is_jandan_user\":1,\"is_tip_user\":0,\"vote_positive\":8,\"vote_negative\":0,\"sub_comment_count\":0,\"images\":null,\"ip_location\":\"山东省临沂市\"},{\"comment_ID\":13022272,\"comment_post_ID\":102312,\"comment_topic\":\"\",\"comment_author\":\"蛋友24d3d405765a\",\"comment_date\":\"2025-03-27 22:37:30\",\"comment_date_int\":1743086250,\"comment_content\":\"没看到最后的时候我还以为是今早7点半死在工位上。\",\"comment_parent\":5877938,\"comment_reply_ID\":0,\"is_jandan_user\":1,\"is_tip_user\":0,\"vote_positive\":0,\"vote_negative\":0,\"sub_comment_count\":0,\"images\":null,\"ip_location\":\"\"}],\"has_next_page\":false}\n", "json": {"code": 0, "hot_tucao": [{"comment_ID": 13020772, "comment_post_ID": 102312, "comment_topic": "", "comment_author": "阳光彩虹小白马", "comment_date": "2025-03-27 13:24:57", "comment_date_int": 1743053097, "comment_content": "  <a href=\"#tucao-13020417\" data-id=\"13020417\" class=\"tucao-link\">@蛋友24cd5cbbf97c</a>  这条树洞跟婚姻有什么关系？。。", "comment_parent": 5877938, "comment_reply_ID": 0, "is_jandan_user": 1, "is_tip_user": 0, "vote_positive": 8, "vote_negative": 0, "sub_comment_count": 0, "images": null, "ip_location": "山东省临沂市"}], "tucao": [{"comment_ID": 13020417, "comment_post_ID": 102312, "comment_topic": "", "comment_author": "蛋友24cd5cbbf97c", "comment_date": "2025-03-27 11:37:25", "comment_date_int": 1743046645, "comment_content": "所以婚姻确实会带来很多问题，单身时候 你只有自己寂寞的问题", "comment_parent": 5877938, "comment_reply_ID": 0, "is_jandan_user": 1, "is_tip_user": 0, "vote_positive": 0, "vote_negative": 5, "sub_comment_count": 0, "images": null, "ip_location": "广东省佛山市"}, {"comment_ID": 13020490, "comment_post_ID": 102312, "comment_topic": "", "comment_author": "菠萝包", "comment_date": "2025-03-27 11:58:22", "comment_date_int": 1743047902, "comment_content": "  <a href=\"#tucao-13020417\" data-id=\"13020417\" class=\"tucao-link\">@蛋友24cd5cbbf97c</a> 多个单身一起玩是不是不寂寞了啊", "comment_parent": 5877938, "comment_reply_ID": 0, "is_jandan_user": 1, "is_tip_user": 0, "vote_positive": 0, "vote_negative": 0, "sub_comment_count": 0, "images": null, "ip_location": "上海市宝山区"}, {"comment_ID": 13020772, "comment_post_ID": 102312, "comment_topic": "", "comment_author": "阳光彩虹小白马", "comment_date": "2025-03-27 13:24:57", "comment_date_int": 1743053097, "comment_content": "  <a href=\"#tucao-13020417\" data-id=\"13020417\" class=\"tucao-link\">@蛋友24cd5cbbf97c</a>  这条树洞跟婚姻有什么关系？。。", "comment_parent": 5877938, "comment_reply_ID": 0, "is_jandan_user": 1, "is_tip_user": 0, "vote_positive": 8, "vote_negative": 0, "sub_comment_count": 0, "images": null, "ip_location": "山东省临沂市"}, {"comment_ID": 13022272, "comment_post_ID": 102312, "comment_topic": "", "comment_author": "蛋友24d3d405765a", "comment_date": "2025-03-27 22:37:30", "comment_date_int": 1743086250, "comment_content": "没看到最后的时候我还以为是今早7点半死在工位上。", "comment_parent": 5877938, "comment_reply_ID": 0, "is_jandan_user": 1, "is_tip_user": 0, "vote_positive": 0, "vote_negative": 0, "sub_comment_count": 0, "images": null, "ip_location": ""}], "has_next_page": false}}}