{
  "jandan": {
    "id": "jandan",
    "name": "jandan",
    "files": [
      "week_2025-04-07.json",
      "week_2025-03-31.json",
      "week_2025-03-24.json"
    ],
    "last_updated": "2025-04-13T16:03:31.414484",
    "file_count": 3
  },
  "reddit": {
    "id": "reddit",
    "name": "reddit",
    "files": [
      "week_2025-03-31.json"
    ],
    "last_updated": "2025-03-31T16:28:26.493483",
    "file_count": 1
  },
  "hackernews": {
    "id": "hackernews",
    "name": "hackernews",
    "files": [
      "week_2026-01-26.json",
      "week_2026-01-19.json",
      "week_2026-01-12.json",
      "week_2026-01-05.json",
      "week_2025-12-29.json",
      "week_2025-12-22.json",
      "week_2025-12-15.json",
      "week_2025-12-08.json",
      "week_2025-12-01.json",
      "week_2025-11-24.json",
      "week_2025-11-17.json",
      "week_2025-11-10.json"
    ],
    "last_updated": "2026-01-29T16:09:01.689583",
    "file_count": 12
  }
}